{
    "name": "uDOO",
    "symbol": "uDOO",
    "contract": "0x0df721639ca2f7ff0e1f618b918a65ffb199ac4e",
    "decimals": 18,
    "logo": "https://assets.coingecko.com/coins/images/3078/large/howdoo.png?1547744057",
    "desc": {
        "en": "ERC20",
        "zh": "ERC20"
    },
    "website": "",
    "whitepaper": "Howdoo is a decentralized social platform for users, content creators, \u0026 advertisers.",
    "invalid": true,
    "links": {
        "twitter": "",
        "telegram": ""
    }
}